{
  "uid": {
    "__TYPE__": "UIDContent",
    "value": "climate"
  },
  "title": {
    "__TYPE__": "FieldContent",
    "value": "indicate",
    "type": "Text"
  },
  "description": {
    "__TYPE__": "FieldContent",
    "value": "board",
    "type": "Text"
  },
  "slices": {
    "__TYPE__": "SliceContentType",
    "value": [
      {
        "key": "content_slice$88ee8519-2cf0-4fed-b73e-4e3d29485dbb",
        "name": "content_slice",
        "widget": {
          "__TYPE__": "SharedSliceContent",
          "variation": "default",
          "primary": {
            "content": {
              "__TYPE__": "StructuredTextContent",
              "value": [
                {
                  "type": "paragraph",
                  "content": {
                    "text": "Excepteur magna velit elit reprehenderit minim aute ea id ut officia veniam ullamco."
                  }
                }
              ]
            }
          },
          "items": [
            {
              "__TYPE__": "GroupItemContent",
              "value": []
            }
          ]
        }
      },
      {
        "key": "hero_slice$5d927127-1033-4062-8e6b-c83ce0ba634c",
        "name": "hero_slice",
        "widget": {
          "__TYPE__": "SharedSliceContent",
          "variation": "default",
          "primary": {
            "intro": {
              "__TYPE__": "StructuredTextContent",
              "value": [
                {
                  "type": "paragraph",
                  "content": {
                    "text": "Ex officia anim irure dolore sint non elit eiusmod nisi qui ea enim Lorem veniam. Pariatur tempor non exercitation veniam deserunt sunt. Ex enim excepteur sint in in culpa ex incididunt adipisicing ea."
                  }
                }
              ]
            },
            "title": {
              "__TYPE__": "StructuredTextContent",
              "value": [
                {
                  "type": "heading1",
                  "content": {
                    "text": "Usual"
                  }
                }
              ]
            },
            "subText": {
              "__TYPE__": "StructuredTextContent",
              "value": [
                {
                  "type": "paragraph",
                  "content": {
                    "text": "Consectetur irure culpa deserunt consectetur ut sunt irure. Occaecat ipsum eiusmod irure est fugiat ex consectetur reprehenderit officia."
                  }
                }
              ]
            },
            "reactifyTitle": {
              "__TYPE__": "BooleanContent",
              "value": true
            }
          },
          "items": [
            {
              "__TYPE__": "GroupItemContent",
              "value": []
            }
          ]
        }
      },
      {
        "key": "angle_slice$d7ca3def-b8da-4fc8-b13f-e26fc717df0d",
        "name": "angle_slice",
        "widget": {
          "__TYPE__": "SharedSliceContent",
          "variation": "default",
          "primary": {},
          "items": [
            {
              "__TYPE__": "GroupItemContent",
              "value": []
            }
          ]
        }
      }
    ]
  }
}