{
  "id": "b2d9bf5f-9a99-404b-b183-af2b0ad99fc0",
  "uid": "qui-iste-impedit",
  "type": "project",
  "data": {
    "thumbnail": {
      "dimensions": {
        "width": 200,
        "height": 200
      },
      "alt": "Placeholder image",
      "copyright": null,
      "url": "https://images.unsplash.com/photo-1471897488648-5eae4ac6686b?w=200&h=200&fit=crop"
    },
    "name": "deploy impactful communities",
    "brief": [
      {
        "type": "paragraph",
        "text": "Ea esse cillum nisi enim est elit. Aliqua est veniam reprehenderit et ullamco ex minim. Irure velit incididunt ex ullamco laborum eu nisi dolore ex consectetur enim minim excepteur sit.",
        "spans": []
      }
    ],
    "startedYear": "maximize efficient infomediaries",
    "endedYear": "deploy turn-key mindshare",
    "url": {
      "link_type": "Web",
      "url": "https://slicemachine.dev"
    },
    "sourceCode": {
      "link_type": "Web",
      "url": "http://google.com"
    },
    "tech": "integrate killer channels"
  }
}